chmutil/createchmimage.py
chmutil/__init__.py
chmutil/createchmjob.py
chmutil/core.py
chmutil/createtrainingmrcstack.py
chmutil/cluster.py
chmutil/image.py
chmutil/chmrunner.py
chmutil/checkchmjob.py
chmutil/mergetilerunner.py
chmutil/mergetiles.py
chmutil/createchmtrainjob.py
chmutil/createprobmapoverlay.py
chmutil-0.8.4.dist-info/metadata.json
chmutil-0.8.4.dist-info/METADATA
chmutil-0.8.4.dist-info/DESCRIPTION.rst
chmutil-0.8.4.dist-info/WHEEL
chmutil-0.8.4.dist-info/top_level.txt
chmutil-0.8.4.dist-info/RECORD
chmutil-0.8.4.data/scripts/createchmimage.py
chmutil-0.8.4.data/scripts/createchmjob.py
chmutil-0.8.4.data/scripts/createtrainingmrcstack.py
chmutil-0.8.4.data/scripts/chmrunner.py
chmutil-0.8.4.data/scripts/checkchmjob.py
chmutil-0.8.4.data/scripts/mergetilerunner.py
chmutil-0.8.4.data/scripts/mergetiles.py
chmutil-0.8.4.data/scripts/createchmtrainjob.py
chmutil-0.8.4.data/scripts/createprobmapoverlay.py
