Metadata-Version: 2.0
Name: chmutil
Version: 0.8.4
Summary: Utility package to run CHM jobs on clusters
Home-page: https://github.com/CRBS/chmutil
Author: Christopher Churas
Author-email: churas@ncmir.ucsd.edu
License: UNKNOWN
Keywords: chmutil
Platform: UNKNOWN
Classifier: Development Status :: 2 - Pre-Alpha
Classifier: Intended Audience :: Developers
Classifier: Natural Language :: English
Classifier: Programming Language :: Python :: 2.7
Classifier: Programming Language :: Python :: 3.3
Classifier: Programming Language :: Python :: 3.4
Classifier: Programming Language :: Python :: 3.5
Classifier: Programming Language :: Python :: 3.6
Requires-Dist: argparse
Requires-Dist: configparser
Requires-Dist: Pillow
